hikari_discord_interactions/__init__.py
hikari_discord_interactions/bot.py
hikari_discord_interactions/command.py
hikari_discord_interactions/context.py
hikari_discord_interactions/return_types.py
hikari_discord_interactions/types.py
hikari_discord_interactions-0.1.5.dist-info/LICENSE
hikari_discord_interactions-0.1.5.dist-info/WHEEL
hikari_discord_interactions-0.1.5.dist-info/METADATA
hikari_discord_interactions-0.1.5.dist-info/RECORD
