Metadata-Version: 2.1
Name: hikari-discord-interactions
Version: 0.1.5
Summary: A Discord interactions library built on top of hikari.
Requires-Python: >=3.10
Requires-Dist: hikari[server]~=2.0.0.dev121
